geopapyrus-0.1.1.dist-info/METADATA
geopapyrus-0.1.1.dist-info/WHEEL
geopapyrus-0.1.1.dist-info/licenses/LICENSE
geopapyrus/__init__.py
geopapyrus/__init__.pyi
geopapyrus/py.typed
geopapyrus/geopapyrus.cpython-310-s390x-linux-gnu.so
geopapyrus-0.1.1.dist-info/RECORD
